{
  "definitions": [
    {
      "title": "API Lookup",
      "id": "apilookup",
      "plugins": {
        "xwalk": {
          "page": {
            "resourceType": "core/fd/components/form/panelcontainer/v1/panelcontainer",
            "template": {
              "jcr:title": "API Lookup",
              "fieldType": "panel",
              "fd:viewType": "apilookup",
              "text": {
                "value": "Text related to the API lookup goes here.",
                "sling:resourceType": "core/fd/components/form/text/v1/text",
                "fieldType": "plain-text",
                "textIsRich": true
              },
              "companyname": {
                "resourceType": "core/fd/components/form/textinput/v1/textinput",
                "jcr:title": "Company Name",
                "fieldType": "plain-text",
                "fd:viewType": "companyname",
                "enabled": true,
                "visible": true
              },
              "dunsnumber": {
                "value": "This is where the DUNS number will be.",
                "sling:resourceType": "core/fd/components/form/text/v1/text",
                "fieldType": "plain-text",
                "textIsRich": true
              }
            }
          }
        }
      }
    }
  ],
  "models": [
    {
      "id": "apilookup",
      "fields": [
        {
          "component": "container",
          "name": "basic",
          "label": "Basic",
          "collapsible": false,
          "fields": [
            {
              "...": "../../models/form-common/_basic-input-fields.json#/fields"
            }
          ]
        },
        {
          "...": "../../models/form-common/_help-container.json"
        }
      ]
    }
  ]
}